autottlcache/__init__.py
autottlcache/cache.py
autottlcache/monitor.py
autottlcache/version.py
autottlcache-1.0.8.dist-info/LICENSE
autottlcache-1.0.8.dist-info/METADATA
autottlcache-1.0.8.dist-info/WHEEL
autottlcache-1.0.8.dist-info/top_level.txt
autottlcache-1.0.8.dist-info/RECORD
